naivepy/__init__.py
naivepy/exceptions.py
naivepy/naivepy.py
naivepy-1.1.dist-info/LICENSE
naivepy-1.1.dist-info/METADATA
naivepy-1.1.dist-info/WHEEL
naivepy-1.1.dist-info/top_level.txt
naivepy-1.1.dist-info/RECORD
